CHANGELOG
MANIFEST.in
Makefile
README.md
README.txt
gpl-3.0.txt
requirements.txt
setup.py
gantt/__init__.py
gantt/gantt.py
gantt/test_gantt.py
gantt/version.py
org2gantt/Orgnode.py
org2gantt/README.org
org2gantt/example.org
org2gantt/org2gantt.py
python_gantt.egg-info/PKG-INFO
python_gantt.egg-info/SOURCES.txt
python_gantt.egg-info/dependency_links.txt
python_gantt.egg-info/requires.txt
python_gantt.egg-info/top_level.txt
python_gantt.egg-info/zip-safe