Metadata-Version: 1.1
Name: python-gantt
Version: 0.5.0
Summary: This is a python class to create gantt chart using SVG.
Home-page: http://xael.org/pages/python-gantt-en.html
Author: Alexandre Norman
Author-email: norman@xael.org
License: gpl-3.0.txt
Keywords: gantt,graphics,scheduling,project management
Platform: Operating System :: OS Independent
Classifier: Development Status :: 5 - Production/Stable
Classifier: Programming Language :: Python
Classifier: Environment :: Console
Classifier: Intended Audience :: Developers
Classifier: Intended Audience :: End Users/Desktop
Classifier: License :: OSI Approved :: GNU General Public License (GPL)
Classifier: Operating System :: OS Independent
Classifier: Topic :: Multimedia :: Graphics :: Editors :: Vector-Based
Classifier: Topic :: Office/Business :: Scheduling
Classifier: Topic :: Scientific/Engineering :: Visualization
